prlgen-2.0.1.dist-info/licenses/LICENSE.txt
stim_list/__init__.py
stim_list/stimlist.py
prlgen-2.0.1.dist-info/METADATA
prlgen-2.0.1.dist-info/WHEEL
prlgen-2.0.1.dist-info/entry_points.txt
prlgen-2.0.1.dist-info/top_level.txt
prlgen-2.0.1.dist-info/RECORD
