Metadata-Version: 2.4
Name: prlgen
Version: 2.0.1
Summary: Pseudo Random List Generator
Home-page: https://github.com/daniel-diaz-ucl/Pseudo-Random-List-Sorting-Algorithm
Author: Daniel Diaz
Author-email: daniel.diaz@ucl.ac.uk
License: GNU GPL v3.0
Keywords: psychology-experiments,pseudo-random-generator,psychology,PsychoPy
Classifier: Development Status :: 5 - Production/Stable
Classifier: Environment :: Console
Classifier: Intended Audience :: Science/Research
Classifier: License :: OSI Approved :: GNU General Public License v3 (GPLv3)
Classifier: Operating System :: MacOS :: MacOS X
Classifier: Operating System :: Microsoft :: Windows
Classifier: Operating System :: POSIX :: Linux
Classifier: Programming Language :: Python :: 3
Classifier: Topic :: Scientific/Engineering
License-File: LICENSE.txt
Dynamic: license-file
